[
	{
		"NAMES": [
		"前向传播"
		],
		"DESCRIPTION": "激发 #y卷积 以及弃牌堆中所有 #y注意力头 的效果。"
	},
	{
        "NAMES": ["卷积"],
        "DESCRIPTION": "#y前向传播 时触发。打出一张带有攻击和格挡的 #y特征图 ，其数值等于弃牌堆中所有牌数值的和的20%乘上 #y平均精度 与 #y损失 之差。"
    },
	{
        "NAMES": ["损失"],
        "DESCRIPTION": "当前模型损失，减小 #r损失 层数有利于提高 #y平均精度 。"
    },
	{
        "NAMES": ["过拟合"],
        "DESCRIPTION": "体现模型对未见数据集的适应程度，过高的 #r过拟合 层数将对战斗不利。"
    },
    {
        "NAMES": ["平均精度"],
        "DESCRIPTION": "模型在测试集上的精度，能提高部分卡牌、能力的效果。"
    },
    {
        "NAMES": ["幻觉"],
        "DESCRIPTION": "手牌变得免费。"
    }
]
